{
  "topicId": "e-water-ocean",
  "isNew": false,
  "newQuiz": [
    {
      "stem": "下表為地球上各水體所占比例（約略值）：海洋 97.2%、冰川與冰帽 2.1%、地下水 0.6%、湖泊河川等地表淡水 0.01%。若某報告稱「人類較易取用的液態淡水（地表河湖＋地下水）」，依表估算其約占全球總水量的比例最接近？",
      "options": [
        "約 0.6%",
        "約 2.1%",
        "約 2.7%",
        "約 3%"
      ],
      "answer": 0,
      "explanation": "較易取用的液態淡水＝地下水 0.6%＋地表淡水 0.01%≈0.61%，最接近 0.6%。占比 2.1% 的是冰川冰帽（固態、難取用），2.7%、3% 則是把冰川也算進淡水總量的數字。",
      "trap": "⚠ 別把『淡水總量(約2.7~3%)』當成『可取用淡水』；冰川冰帽雖是淡水卻是固態且多在極區，題目問的是液態、易取用的部分，只能算地下水＋地表淡水。"
    },
    {
      "stem": "在水循環中，下列哪一組『過程—能量變化—對周遭環境的熱效應』全部正確？",
      "options": [
        "蒸發：吸熱、使周圍降溫；凝結：放熱、使周圍增溫",
        "蒸發：放熱、使周圍增溫；凝結：吸熱、使周圍降溫",
        "蒸發：吸熱、使周圍增溫；凝結：放熱、使周圍降溫",
        "蒸發與凝結都吸熱，故都使周圍降溫"
      ],
      "answer": 0,
      "explanation": "蒸發是液→氣，需吸收汽化熱，會帶走周圍熱量使周遭降溫（如流汗散熱）；凝結是氣→液，會釋放潛熱使周遭增溫（如雲形成時放熱）。",
      "trap": "⚠ 吸熱不等於『讓周圍變熱』。蒸發吸熱是『從周圍吸走熱』，所以周圍反而降溫；凝結放熱才使周圍增溫。把吸/放熱與周圍冷暖方向配反是常見錯誤。"
    },
    {
      "stem": "甲、乙兩地緯度相近，甲位於大陸西岸並有寒流流經，乙位於大陸東岸並有暖流流經。在其他條件相近下，最合理的推論是？",
      "options": [
        "乙岸的年均溫通常高於甲岸，因暖流帶來較溫暖的海水",
        "甲岸的年均溫通常高於乙岸，因寒流會使空氣上升增溫",
        "兩岸氣候必相同，因為緯度相近",
        "寒流流經之處一定比暖流流經之處潮濕多雨"
      ],
      "answer": 0,
      "explanation": "暖流由低緯流向高緯，會把溫暖海水帶到沿岸、使沿岸增溫且常較濕潤；寒流由高緯流向低緯、使沿岸降溫且常較乾涼。故有暖流的乙岸年均溫通常高於有寒流的甲岸。",
      "trap": "⚠ 洋流會調節沿岸氣候，所以『緯度相近氣候就相同』是錯的。寒流降溫且偏乾，暖流增溫且偏濕，別把寒流誤判為帶來增溫或多雨。"
    },
    {
      "stem": "某地今天 03:10 出現一次滿潮。已知相鄰兩次滿潮約間隔 12 小時 25 分。則『今天當天之內』還會再出現幾次滿潮？這些滿潮的時刻最接近下列哪一組？",
      "options": [
        "再 1 次，約 15:35",
        "再 2 次，約 15:35 與隔日 04:00",
        "再 1 次，約 15:10",
        "再 2 次，約 09:22 與 15:35"
      ],
      "answer": 0,
      "explanation": "下一次滿潮＝03:10＋12 時 25 分＝15:35，仍在當天；再下一次為 15:35＋12 時 25 分≈隔日 04:00，已跨日不算。故當天之內只再出現 1 次，約 15:35。",
      "trap": "⚠ 滿潮間隔約 12 時 25 分（非 6 小時，6 小時是滿潮到乾潮）。03:10 之後當天只塞得下一次（15:35），第三次已落到隔日，別誤算成兩次。"
    },
    {
      "stem": "下列關於『大潮、小潮』與月相關係的敘述，何者完全正確？",
      "options": [
        "新月與滿月時為大潮，因日、地、月接近一直線使引潮力疊加",
        "上弦與下弦時為大潮，因太陽與月球引潮力疊加",
        "只有滿月才會大潮，新月時因看不到月亮故無大潮",
        "大潮、小潮與月相無關，僅由月地距離決定"
      ],
      "answer": 0,
      "explanation": "新月（朔）與滿月（望）時日地月接近一直線，太陽與月球引潮力同方向疊加，潮差最大為大潮；上下弦時三者成直角，引潮力部分抵消而成小潮。新月一樣會大潮，與看不看得到月亮無關。",
      "trap": "⚠ 大潮不是只有滿月！新月（看不到月亮）同樣成一直線、同樣大潮。上下弦才是小潮（成直角抵消），別把大小潮配反，也別誤以為新月無潮汐效應。"
    },
    {
      "stem": "甲、乙、丙三同學描述潮汐成因：甲說『主要由太陽引力造成』；乙說『主要由月球引力造成，因月球較近』；丙說『一天大約有兩次漲潮、兩次退潮』。下列判斷何者正確？",
      "options": [
        "乙、丙正確，甲錯誤",
        "甲、丙正確，乙錯誤",
        "三人皆正確",
        "只有丙正確"
      ],
      "answer": 0,
      "explanation": "潮汐主因是月球引力（月球雖小但距地球近，引潮力大於太陽），故乙對、甲錯；一天約有兩次漲潮兩次退潮，丙也對。",
      "trap": "⚠ 太陽質量遠大於月球，但引潮力與距離立方成反比，月球較近故影響較大。別被『太陽比較大』誤導而選甲；潮汐主角是月球。"
    },
    {
      "stem": "下圖情境：一密閉透明箱底部放一盤鹽水，置於陽光下數小時。觀察到箱壁出現水珠、盤中鹽水變濃（鹽未減少）。此實驗最能模擬水循環中的哪兩個過程，以及鹽的去向為何？",
      "options": [
        "蒸發與凝結；鹽留在盤中不隨水蒸氣上升，故鹽水變濃",
        "蒸發與降水；鹽隨水蒸氣蒸發到箱壁",
        "凝結與入滲；鹽溶於箱壁水珠中",
        "升華與凝華；鹽因受熱昇華消失"
      ],
      "answer": 0,
      "explanation": "陽光使盤中水蒸發（液→氣）上升，遇較冷箱壁凝結成水珠（氣→液），對應水循環的蒸發與凝結。蒸發時只有水變成氣體、鹽不會隨之蒸發，故盤中鹽量不變、水減少而濃度升高。這也說明海水蒸發後降下的雨是淡水。",
      "trap": "⚠ 蒸發的是『純水』，鹽留在原處，所以鹽水會變濃而非鹽消失或隨氣上升。這正是『海水蒸發、降雨為淡水』的道理，別誤以為鹽會跟著蒸發。"
    },
    {
      "stem": "若地球的自轉軸傾角不變，但月球忽然消失（僅剩太陽的引潮作用），下列關於潮汐的推論最合理的是？",
      "options": [
        "仍有潮汐但潮差變小，且大潮小潮的『月相規律』消失",
        "潮汐完全消失，因為潮汐只由月球造成",
        "潮差變得比原本更大，因為少了月球的干擾",
        "漲退潮次數會增加為一天四次"
      ],
      "answer": 0,
      "explanation": "太陽也有引潮力（約為月球的一半），故月球消失後仍有由太陽造成的潮汐，但因主要的月球貢獻不見了，整體潮差變小；且大潮小潮原本依賴日地月相對位置（月相），月球消失後這種週期規律也隨之消失。",
      "trap": "⚠ 別以為『潮汐＝只有月球』。太陽同樣能造成潮汐，只是較弱。月球消失是潮差變小、月相週期消失，而非潮汐歸零或變大。"
    },
    {
      "stem": "海洋對全球氣候的『調節』作用，與下列哪一項水的物理性質最直接相關？並可由此性質推論沿海與內陸氣溫的何種差異？",
      "options": [
        "水的比熱大，故沿海日夜及季節溫差通常小於內陸",
        "水的密度大，故沿海氣溫永遠高於內陸",
        "水的沸點高，故沿海不會結冰",
        "水的表面張力大，故沿海多霧"
      ],
      "answer": 0,
      "explanation": "水的比熱大，吸放相同熱量時溫度變化小，海洋如同巨大的『溫度緩衝器』；因此鄰海地區升溫降溫都較慢、日夜與季節溫差較小，內陸（陸地比熱小）則溫差大。這是海洋調節氣候的關鍵。",
      "trap": "⚠ 調節氣候靠的是水的『比熱大』而非密度或沸點。比熱大代表溫差小（緩衝），所以沿海溫差小於內陸，不是沿海一定比較熱。"
    },
    {
      "stem": "某條河流上游因長期超抽地下水與大量鋪設不透水柏油，與未開發前相比，同樣一場暴雨後最可能出現的水循環變化是？",
      "options": [
        "入滲減少、地表逕流增加，下游河川水位上升更快、更易釀成洪患",
        "入滲增加、地表逕流減少，下游更不易淹水",
        "蒸發完全停止，水循環中斷",
        "降水量大幅增加，因為柏油會吸水"
      ],
      "answer": 0,
      "explanation": "不透水鋪面使雨水難以入滲補注地下水，雨水多轉為地表逕流並快速匯入河川，造成河川水位短時間暴漲、增加洪患風險；同時地下水補注減少。這是都市化對水循環的典型衝擊。",
      "trap": "⚠ 柏油是不透水、會『減少入滲、增加逕流』，不是吸水。逕流增加→更易淹水，而非更不易淹；降水量由氣象決定，不會因鋪柏油而增加。"
    },
    {
      "stem": "已知潮汐每天會比前一天延後約 50 分鐘（因月球同向公轉）。若某地週一的第一次滿潮在 06:00，則『週四』的第一次滿潮最接近下列哪個時刻？",
      "options": [
        "約 08:30",
        "約 06:50",
        "約 03:30",
        "約 09:00"
      ],
      "answer": 0,
      "explanation": "每天延後約 50 分鐘，由週一到週四共經過 3 天，延後 3×50＝150 分鐘＝2 小時 30 分。06:00＋2 時 30 分＝08:30。",
      "trap": "⚠ 是『往後延』不是提早，且要乘正確天數（週一到週四是 3 天，不是 4 天）。算成 06:50（只延一天）或往前推到 03:30 都是常見錯誤。"
    },
    {
      "stem": "下列關於黑潮（流經臺灣東岸的暖流）的敘述，何者正確？",
      "options": [
        "屬暖流，由低緯流向高緯，使流經海域水溫偏高並有助沿岸漁業",
        "屬寒流，由高緯流向低緯，使臺灣東岸氣候變冷",
        "是淡水河流，發源於臺灣中央山脈",
        "由地球自轉直接『推動』海水，與水溫、風帶無關"
      ],
      "answer": 0,
      "explanation": "黑潮是強勁的暖流，由低緯度往高緯度流動，流經臺灣東部海域使水溫偏高，暖水與營養條件常帶來豐富漁業資源並調節沿岸氣候使其較溫暖。它是海洋中的洋流而非陸上河流。",
      "trap": "⚠ 黑潮是『暖流』（低緯→高緯、增溫）不是寒流，也不是淡水河。洋流由風帶、海水溫鹽差異等驅動，並非地球自轉單獨『推水』，別選與水溫無關的敘述。"
    }
  ]
}
